JMESPathLibrary/__init__.py
JMESPathLibrary/keywords.py
robotframework_jmespath-0.1.0.dist-info/METADATA
robotframework_jmespath-0.1.0.dist-info/WHEEL
robotframework_jmespath-0.1.0.dist-info/licenses/LICENSE
robotframework_jmespath-0.1.0.dist-info/RECORD
