Metadata-Version: 2.4
Name: robotframework-jmespath
Version: 0.1.0
Summary: A Robot Framework library for JMESPath-based JSON querying, providing high-performance alternative to JSONPath
Project-URL: homepage, https://github.com/netascode/robotframework-jmespath
Project-URL: repository, https://github.com/netascode/robotframework-jmespath
Project-URL: documentation, https://github.com/netascode/robotframework-jmespath
Project-URL: issues, https://github.com/netascode/robotframework-jmespath/issues
Author-email: Oliver Boehmer <oboehmer@cisco.com>
Maintainer-email: Oliver Boehmer <oboehmer@cisco.com>
License: MPL-2.0
License-File: LICENSE
Keywords: jmespath,json,query,robot,robotframework,testing
Classifier: Development Status :: 4 - Beta
Classifier: Framework :: Robot Framework
Classifier: Framework :: Robot Framework :: Library
Classifier: Intended Audience :: Developers
Classifier: License :: OSI Approved :: Mozilla Public License 2.0 (MPL 2.0)
Classifier: Operating System :: OS Independent
Classifier: Programming Language :: Python :: 3
Classifier: Programming Language :: Python :: 3.10
Classifier: Programming Language :: Python :: 3.11
Classifier: Programming Language :: Python :: 3.12
Classifier: Programming Language :: Python :: 3.13
Classifier: Topic :: Software Development :: Quality Assurance
Classifier: Topic :: Software Development :: Testing
Requires-Python: >=3.10
Requires-Dist: jmespath>=1.0.1
Requires-Dist: robotframework>=5.0
Provides-Extra: dev
Requires-Dist: bandit[toml]>=1.8.6; extra == 'dev'
Requires-Dist: mypy>=1.17.1; extra == 'dev'
Requires-Dist: pre-commit>=4.3.0; extra == 'dev'
Requires-Dist: pytest-cov>=6.2.1; extra == 'dev'
Requires-Dist: pytest-mock>=3.15.0; extra == 'dev'
Requires-Dist: pytest>=8.4.2; extra == 'dev'
Requires-Dist: robotframework>=5.0; extra == 'dev'
Requires-Dist: ruff>=0.12.12; extra == 'dev'
